rapidgbm/__init__.py
rapidgbm/examples/classification.ipynb
rapidgbm/examples/regression.ipynb
rapidgbm/metrics/__init__.py
rapidgbm/metrics/metric_funcs.py
rapidgbm/metrics/metric_utils.py
rapidgbm/tuner.py
rapidgbm/utility/__init__.py
rapidgbm/utility/optuna_tools.py
rapidgbm/utility/plottingmixin.py
rapidgbm/utility/printer.py
rapidgbm/utility/timer.py
rapidgbm/utility/validatormixin.py
rapidgbm/utility/validators.py
rapidgbm-0.1.0.dist-info/METADATA
rapidgbm-0.1.0.dist-info/WHEEL
rapidgbm-0.1.0.dist-info/LICENSE.md
rapidgbm-0.1.0.dist-info/RECORD
