Metadata-Version: 2.1
Name: rapidgbm
Version: 0.1.0
Summary: RapidGBM is a powerful Python package designed to streamline the process of tuning LightGBM models using the optimization framework Optuna.
License: LICENSE.md
Author: Daniel Porsmose
Requires-Python: >=3.9,<3.13
Classifier: License :: Other/Proprietary License
Classifier: Programming Language :: Python :: 3
Classifier: Programming Language :: Python :: 3.9
Classifier: Programming Language :: Python :: 3.10
Classifier: Programming Language :: Python :: 3.11
Requires-Dist: lightgbm (>=3.3.0,<5.0.0)
Requires-Dist: matplotlib (>=3.5.2,<4.0.0)
Requires-Dist: numpy (>=1.13.0,<3.0.0)
Requires-Dist: optuna (>=2.10.0,<4.0.0)
Requires-Dist: optuna-integration (>=3.2.0,<4.0.0)
Requires-Dist: pandas (>=1.5.0,<3.0.0)
Requires-Dist: scikit-learn (>=0.23.2,<2.0.0)
